botovod/__init__.py
botovod/botovod.py
botovod/dialogs.py
botovod/exceptions.py
botovod/agents/__init__.py
botovod/agents/agents.py
botovod/agents/telegram.py
botovod/agents/vk.py
botovod/dbdrivers/__init__.py
botovod/dbdrivers/dbdrivers.py
botovod/dbdrivers/django.py
botovod/dbdrivers/gino.py
botovod/dbdrivers/sqlalchemy.py
botovod/extensions/__init__.py
botovod/extensions/djangoapp/__init__.py
botovod/extensions/djangoapp/botovod/__init__.py
botovod/extensions/djangoapp/botovod/models.py
botovod/utils/__init__.py
botovod/utils/emoji.py
botovod/utils/handlers.py
botovod-0.1.11.dist-info/LICENSE
botovod-0.1.11.dist-info/METADATA
botovod-0.1.11.dist-info/WHEEL
botovod-0.1.11.dist-info/top_level.txt
botovod-0.1.11.dist-info/RECORD
