Metadata-Version: 2.1
Name: botovod
Version: 0.1.11
Summary: UNKNOWN
Home-page: https://github.com/OlegYurchik/botovod
Author: Oleg Yurchik
Author-email: oleg.yurchik@protonmail.com
License: UNKNOWN
Platform: UNKNOWN
Requires-Dist: aiofiles
Requires-Dist: aiohttp
Requires-Dist: requests
